pytest_stochastics/__init__.py
pytest_stochastics/collector.py
pytest_stochastics/main.py
pytest_stochastics/runner.py
pytest_stochastics/runner_data.py
pytest_stochastics-0.4.4.dist-info/LICENSE
pytest_stochastics-0.4.4.dist-info/METADATA
pytest_stochastics-0.4.4.dist-info/WHEEL
pytest_stochastics-0.4.4.dist-info/entry_points.txt
pytest_stochastics-0.4.4.dist-info/RECORD
