Metadata-Version: 2.1
Name: pytest-stochastics
Version: 0.4.4
Summary: pytest plugin that allows selectively running tests several times and accepting *some* failures.
Author: MCNatsu
Author-email: nathan@emcie.co
Requires-Python: >=3.10,<4.0
Classifier: Programming Language :: Python :: 3
Classifier: Programming Language :: Python :: 3.10
Classifier: Programming Language :: Python :: 3.11
Classifier: Programming Language :: Python :: 3.12
Requires-Dist: dataclasses-json (>=0.6.7,<0.7.0)
Requires-Dist: mypy (>=1.11.1,<2.0.0)
Requires-Dist: pytest (>=8.0.0,<9.0.0)
Requires-Dist: rich (>=13.9.3,<14.0.0)
